{
  "id": "est-li-lyudi-kotorye-ne-hotyat-moih-izmeneniy",
  "type": "question",
  "title": "Есть ли люди, которые не хотят моих изменений?",
  "answerType": "multiple",
  "source": "text",
  "answers": [
    {
      "id": "semya-soprotivlyaetsya",
      "value": {
        "male": "семья сопротивляется",
        "female": "семья сопротивляется"
      },
      "exportedValue": {
        "male": "У меня семья сопротивляется",
        "female": "У меня семья сопротивляется"
      },
      "hint": "Семья, привыкшая к определенной роли; друзья, боящиеся потерять меня. Социальное сопротивление моим эмоциональным изменениям",
      "exercise": ""
    },
    {
      "id": "druzya-protiv",
      "value": {
        "male": "друзья против",
        "female": "друзья против"
      },
      "exportedValue": {
        "male": "У меня друзья против",
        "female": "У меня друзья против"
      },
      "hint": "Семья, привыкшая к определенной роли; друзья, боящиеся потерять меня. Социальное сопротивление моим эмоциональным изменениям",
      "exercise": ""
    },
    {
      "id": "kollegi-ne-ponimayut",
      "value": {
        "male": "коллеги не понимают",
        "female": "коллеги не понимают"
      },
      "exportedValue": {
        "male": "У меня коллеги не понимают",
        "female": "У меня коллеги не понимают"
      },
      "hint": "Семья, привыкшая к определенной роли; друзья, боящиеся потерять меня. Социальное сопротивление моим эмоциональным изменениям",
      "exercise": ""
    },
    {
      "id": "vse-podderzhivayut",
      "value": {
        "male": "все поддерживают",
        "female": "все поддерживают"
      },
      "exportedValue": {
        "male": "У меня все поддерживают",
        "female": "У меня все поддерживают"
      },
      "hint": "Семья, привыкшая к определенной роли; друзья, боящиеся потерять меня. Социальное сопротивление моим эмоциональным изменениям",
      "exercise": ""
    }
  ]
}