{
  "id": "kak-ya-zhestikuliruyu-v-spokoynom-i-emotsionalnom-",
  "type": "question",
  "title": "Как я жестикулирую в спокойном и эмоциональном состоянии?",
  "answerType": "single",
  "source": "text",
  "answers": [
    {
      "id": "zhesty-stanovyatsya-aktivnee",
      "value": {
        "male": "жесты становятся активнее",
        "female": "жесты становятся активнее"
      },
      "exportedValue": {
        "male": "У меня жесты становятся активнее",
        "female": "У меня жесты становятся активнее"
      },
      "hint": "Изменения в амплитуде, частоте, характере жестов",
      "exercise": ""
    },
    {
      "id": "naoborot-sderzhivayus",
      "value": {
        "male": "наоборот сдерживаюсь",
        "female": "наоборот сдерживаюсь"
      },
      "exportedValue": {
        "male": "У меня наоборот сдерживаюсь",
        "female": "У меня наоборот сдерживаюсь"
      },
      "hint": "Изменения в амплитуде, частоте, характере жестов",
      "exercise": ""
    },
    {
      "id": "zhestikulyatsiya-ne-menyaetsya",
      "value": {
        "male": "жестикуляция не меняется",
        "female": "жестикуляция не меняется"
      },
      "exportedValue": {
        "male": "У меня жестикуляция не меняется",
        "female": "У меня жестикуляция не меняется"
      },
      "hint": "Изменения в амплитуде, частоте, характере жестов",
      "exercise": ""
    },
    {
      "id": "teryayu-kontrol-nad-zhestami",
      "value": {
        "male": "теряю контроль над жестами",
        "female": "теряю контроль над жестами"
      },
      "exportedValue": {
        "male": "У меня теряю контроль над жестами",
        "female": "У меня теряю контроль над жестами"
      },
      "hint": "Изменения в амплитуде, частоте, характере жестов",
      "exercise": ""
    }
  ]
}