{
  "id": "kto-iz-lyudey-sposoben-mgnovenno-podnyat-nastroeni",
  "type": "question",
  "title": "Кто из людей способен мгновенно поднять настроение персонажу?",
  "answerType": "multiple",
  "source": "text",
  "answers": [
    {
      "id": "blizkie-druzya",
      "value": {
        "male": "близкие друзья",
        "female": "близкие друзья"
      },
      "exportedValue": {
        "male": "У меня близкие друзья",
        "female": "У меня близкие друзья"
      },
      "hint": "Подумайте о \"витаминах для души\" - кто и что заряжает персонажа позитивом. Люди как живые антидепрессанты - кто обладает волшебной способностью исцелять одним присутствием",
      "exercise": ""
    },
    {
      "id": "deti",
      "value": {
        "male": "дети",
        "female": "дети"
      },
      "exportedValue": {
        "male": "У меня дети",
        "female": "У меня дети"
      },
      "hint": "Подумайте о \"витаминах для души\" - кто и что заряжает персонажа позитивом. Люди как живые антидепрессанты - кто обладает волшебной способностью исцелять одним присутствием",
      "exercise": ""
    },
    {
      "id": "opredelennyy-tip-lyudey",
      "value": {
        "male": "определенный тип людей",
        "female": "определенный тип людей"
      },
      "exportedValue": {
        "male": "У меня определенный тип людей",
        "female": "У меня определенный тип людей"
      },
      "hint": "Подумайте о \"витаминах для души\" - кто и что заряжает персонажа позитивом. Люди как живые антидепрессанты - кто обладает волшебной способностью исцелять одним присутствием",
      "exercise": ""
    },
    {
      "id": "harizmatichnye-lichnosti",
      "value": {
        "male": "харизматичные личности",
        "female": "харизматичные личности"
      },
      "exportedValue": {
        "male": "У меня харизматичные личности",
        "female": "У меня харизматичные личности"
      },
      "hint": "Подумайте о \"витаминах для души\" - кто и что заряжает персонажа позитивом. Люди как живые антидепрессанты - кто обладает волшебной способностью исцелять одним присутствием",
      "exercise": ""
    },
    {
      "id": "nikto-ne-mozhet",
      "value": {
        "male": "никто не может",
        "female": "никто не может"
      },
      "exportedValue": {
        "male": "У меня никто не может",
        "female": "У меня никто не может"
      },
      "hint": "Подумайте о \"витаминах для души\" - кто и что заряжает персонажа позитивом. Люди как живые антидепрессанты - кто обладает волшебной способностью исцелять одним присутствием",
      "exercise": ""
    }
  ]
}