{
  "id": "mozhet-li-prisposablivatsya-k-izmeneniyam",
  "type": "question",
  "title": "Может ли приспосабливаться к изменениям?",
  "answerType": "single",
  "source": "text",
  "answers": [
    {
      "id": "legko-adaptiruetsya",
      "value": {
        "male": "легко адаптируется",
        "female": "легко адаптируется"
      },
      "exportedValue": {
        "male": "У меня легко адаптируется",
        "female": "У меня легко адаптируется"
      },
      "hint": "Эмоциональная адаптивность vs ригидность в меняющихся обстоятельствах",
      "exercise": ""
    },
    {
      "id": "s-trudom-prisposablivaetsya",
      "value": {
        "male": "с трудом приспосабливается",
        "female": "с трудом приспосабливается"
      },
      "exportedValue": {
        "male": "У меня с трудом приспосабливается",
        "female": "У меня с трудом приспосабливается"
      },
      "hint": "Эмоциональная адаптивность vs ригидность в меняющихся обстоятельствах",
      "exercise": ""
    },
    {
      "id": "emotsionalno-lomaetsya",
      "value": {
        "male": "эмоционально \"ломается\"",
        "female": "эмоционально \"ломается\""
      },
      "exportedValue": {
        "male": "У меня эмоционально \"ломается\"",
        "female": "У меня эмоционально \"ломается\""
      },
      "hint": "Эмоциональная адаптивность vs ригидность в меняющихся обстоятельствах",
      "exercise": ""
    },
    {
      "id": "izbegaet-izmeneniy",
      "value": {
        "male": "избегает изменений",
        "female": "избегает измененая"
      },
      "exportedValue": {
        "male": "У меня избегает изменений",
        "female": "У меня избегает измененая"
      },
      "hint": "Эмоциональная адаптивность vs ригидность в меняющихся обстоятельствах",
      "exercise": ""
    }
  ]
}