{
  "id": "vliyayut-li-bolezni-fizicheskie-izmeneniya",
  "type": "question",
  "title": "Влияют ли болезни, физические изменения?",
  "answerType": "single",
  "source": "text",
  "answers": [
    {
      "id": "silno-vliyayut-na-emotsii",
      "value": {
        "male": "сильно влияют на эмоции",
        "female": "сильно влияют на эмоции"
      },
      "exportedValue": {
        "male": "У меня сильно влияют на эмоции",
        "female": "У меня сильно влияют на эмоции"
      },
      "hint": "Психосоматические факторы трансформации",
      "exercise": ""
    },
    {
      "id": "umerenno-vliyayut",
      "value": {
        "male": "умеренно влияют",
        "female": "умеренно влияют"
      },
      "exportedValue": {
        "male": "У меня умеренно влияют",
        "female": "У меня умеренно влияют"
      },
      "hint": "Психосоматические факторы трансформации",
      "exercise": ""
    },
    {
      "id": "ne-svyazyvaet-fizicheskoe-i-emotsionalnoe",
      "value": {
        "male": "не связывает физическое и эмоциональное",
        "female": "не связывает физическое и эмоциональное"
      },
      "exportedValue": {
        "male": "У меня не связывает физическое и эмоциональное",
        "female": "У меня не связывает физическое и эмоциональное"
      },
      "hint": "Психосоматические факторы трансформации",
      "exercise": ""
    },
    {
      "id": "kompensiruet-fizicheskie-problemy",
      "value": {
        "male": "компенсирует физические проблемы",
        "female": "компенсирует физические проблемы"
      },
      "exportedValue": {
        "male": "У меня компенсирует физические проблемы",
        "female": "У меня компенсирует физические проблемы"
      },
      "hint": "Психосоматические факторы трансформации",
      "exercise": ""
    }
  ]
}